password_cli_app/__init__.py
password_cli_app/database.py
password_cli_app/main.py
password_cli_app/models.py
password_cli_app/security.py
password_cli_app-0.1.1.dist-info/METADATA
password_cli_app-0.1.1.dist-info/WHEEL
password_cli_app-0.1.1.dist-info/entry_points.txt
password_cli_app-0.1.1.dist-info/RECORD
