Metadata-Version: 2.3
Name: password-cli-app
Version: 0.1.1
Summary: Secure password generator CLI
Author: lucifermorninstar
Author-email: iamanaiyelu@gmail.com
Requires-Python: >=3.10,<4.0
Classifier: Programming Language :: Python :: 3
Classifier: Programming Language :: Python :: 3.10
Classifier: Programming Language :: Python :: 3.11
Classifier: Programming Language :: Python :: 3.12
Classifier: Programming Language :: Python :: 3.13
Requires-Dist: argon2-cffi (>=23.1.0,<24.0.0)
Requires-Dist: cryptography (>=44,<45)
Requires-Dist: passlib (>=1.7.4,<2.0.0)
Requires-Dist: rich (>=13.9.4,<14.0.0)
Requires-Dist: sqlalchemy (>=2.0,<3.0)
Requires-Dist: tabulate (>=0.9,<0.10)
Requires-Dist: typer (>=0.15,<0.16)
